[
    {
        "class": "1",
        "subject": "Kunst",
        "month": "",
        "theme": "P천hiv채rvid",
        "link": "https://learningapps.org/display?v=p5inzaab521"
    },
    {
        "class": "1",
        "subject": "Kunst",
        "month": "",
        "theme": "V채rvid",
        "link": "https://learningapps.org/display?v=pjtvniven21"
    },
    {
        "class": "1",
        "subject": "Kunst",
        "month": "",
        "theme": "V채rvide segamine 1",
        "link": "https://learningapps.org/display?v=p4h0bhf6c21"
    }
]